Hw1/design.sv
module decoder_2_4(E , In , Out);

    input E;            //宣告輸入E
    input [1:0] In;     //宣告輸入In[0],In[1]
    output [3:0] Out;   //宣告輸出Out[0]~Out[3]
    wire [3:0] Out;     //宣告輸出Out為連接線

    assign Out = E ? 1'b1 << In : 4'h0;

endmodule

module decoder_3_8(E , In , Out);

    input E;            
    input [2:0] In;     
    output [7:0] Out;   
    wire E1, G1 , G2;   
    
    not u1(E1, In[2]);      //致能線E1與輸入In[2]NOT
    and a1(G1, E, In[2]);   //致能線E1與輸入In[2]NOT
    and a2(G2, E, E1);      //致能線E與輸入E1AND

    decoder_2_4 block1(G1 , In[1 : 0] , Out[7 : 4]);        //Out[7:4]=G1 & In[0:1]輸入decoder_2_4
    decoder_2_4 block2(G2 , In[1 : 0] , Out[3 : 0]);        //Out[3:0]=G2 & In[0:1]輸入decoder_2_4

endmodule

//clock
module clkgen(clka, clkb, clka_out, clkb_out);

    input clka, clkb;           //宣告輸入clka及clkb
    output clka_out, clkb_out;  //宣告輸出clka_out及clkb_out
    reg clka_out, clkb_out;     //將clka_out及clkb_out連接暫存器

    always @(clka) begin        //always當@()有括弧裡的變數時執行

        clka_out = clka;
    
    end
    
    always @(clkb) begin

        clkb_out = clkb;

    end

endmodule

Hw1/textbench.sv
module decoder_3_8_tb;

    reg E_tb;                   //宣告暫存器E_tb
    reg clka, clkb;             //宣告暫存器clka及clkb
    reg [2:0] In_tb;            //宣告暫存器In_tb[2]~In_tb[0]
    wire [7:0] Out_tb;          //宣告連接線Out_tb[7]~Out_tb[0]
    wire clka_out, clkb_out;    //宣告連接線clka_out及clkb_out

    decoder_3_8 decoder_1(.E(E_tb), .In(In_tb), .Out(Out_tb));
    clkgen clkgen_1(.clka(clka), .clkb(clkb), .clka_out(clka_out), .clkb_out(clkb_out));

    initial begin
                            //預設clka及clkb為1位元的0
        clka = 1'b0; 
        clkb = 1'b0;

    end

    always begin

        #10 clka = ~clka;   //延遲10秒後clka=NOT

    end

    always begin

        #20 clkb = ~clkb;

    end

    initial begin

        #0 E_tb = 0; In_tb = 3'b000;            //預設致能為0，三輸入為000,延遲十秒後預設致能為1，三輸入為000
        #10 E_tb = 1; In_tb = 3'b000;
        #10 E_tb = 1; In_tb = 3'b001;
        #10 E_tb = 1; In_tb = 3'b010;
        #10 E_tb = 1; In_tb = 3'b011;
        #10 E_tb = 1; In_tb = 3'b100;
        #10 E_tb = 1; In_tb = 3'b101;
        #10 E_tb = 1; In_tb = 3'b110;
        #10 E_tb = 1; In_tb = 3'b111;
        #10 $finish;

    end

    initial begin

        $dumpfile("decoder.vcd");
        $dumpvars(0, decoder_1);
        $dumpvars(0, clkgen_1);
        
    end

endmodule

Hw1/decoder.vcd
$date
	Wed Mar 30 12:13:29 2022
$end
$version
	Icarus Verilog
$end
$timescale
	1s
$end
$scope module decoder_3_8_tb $end
$scope module decoder_1 $end
$var wire 1 ! E $end
$var wire 1 " E1 $end
$var wire 1 # G1 $end
$var wire 1 $ G2 $end
$var wire 3 % In [2:0] $end
$var wire 8 & Out [7:0] $end
$scope module block1 $end
$var wire 1 # E $end
$var wire 2 ' In [1:0] $end
$var wire 4 ( Out [3:0] $end
$upscope $end
$scope module block2 $end
$var wire 1 $ E $end
$var wire 2 ) In [1:0] $end
$var wire 4 * Out [3:0] $end
$upscope $end
$upscope $end
$upscope $end
$scope module decoder_3_8_tb $end
$scope module clkgen_1 $end
$var wire 1 + clka $end
$var wire 1 , clkb $end
$var reg 1 - clka_out $end
$var reg 1 . clkb_out $end
$upscope $end
$upscope $end
$enddefinitions $end
#0
$dumpvars
0.
0-
0,
0+
b0 *
b0 )
b0 (
b0 '
b0 &
b0 %
0$
0#
1"
0!
$end
#10
b1 &
b1 *
1$
1-
1!
1+
#20
b10 &
b10 *
b1 '
b1 )
0-
1.
b1 %
0+
1,
#30
b100 &
b100 *
b10 '
b10 )
1-
b10 %
1+
#40
b1000 &
b1000 *
b11 '
b11 )
0-
0.
b11 %
0+
0,
#50
0$
b1 (
0"
1#
b10000 &
b0 *
b0 '
b0 )
1-
b100 %
1+
#60
b100000 &
b10 (
b1 '
b1 )
0-
1.
b101 %
0+
1,
#70
b1000000 &
b100 (
b10 '
b10 )
1-
b110 %
1+
#80
b10000000 &
b1000 (
b11 '
b11 )
0-
0.
b111 %
0+
0,
