Hw3/design.sv
// Code your design here
module voter_if (I, O);
input [3:0] I; // I 4 men
output [3:1] O; // O Result
reg [3:1] O;

always@ (I)
    begin
        case(I)
        4'b0000: O = 3'b100;
        4'b0001: O = 3'b100;
        4'b0010: O = 3'b100;
        4'b0011: O = 3'b010;
        4'b0100: O = 3'b100;    
        4'b0101: O = 3'b010;
        4'b0110: O = 3'b010;
        4'b0111: O = 3'b001;
        4'b1000: O = 3'b100;
        4'b1001: O = 3'b010;
        4'b1010: O = 3'b010;
        4'b1011: O = 3'b001;
        4'b1100: O = 3'b010;
        4'b1101: O = 3'b001;      
        4'b1101: O = 3'b001;
        4'b1111: O = 3'b001;   
        endcase            
    end
endmodule

HM3/testbench.sv
// Code your testbench here
// or browse Examples
module RTL_tb;

    reg [3:0] I;        //輸入
    wire [2:0] O;      //輸出

//產生波型
initial begin
    #0 I = 4'b0000;
    #1 I = 4'b0001;
    #1 I = 4'b0010;
    #1 I = 4'b0011;
    #1 I = 4'b0100;
    #1 I = 4'b0101;
    #1 I = 4'b0110;
    #1 I = 4'b0111;
    #1 I = 4'b1000;
    #1 I = 4'b1001;
    #1 I = 4'b1010;
    #1 I = 4'b1011;
    #1 I = 4'b1100;
    #1 I = 4'b1101;
    #1 I = 4'b1110;
    #1 I = 4'b1111;
    #1 $finish;
end
voter_if RTL_tb(.I(I), .O(O));      //輸入RTL.v檔的輸入輸出

initial begin
    $dumpfile("RTL.vcd");
    $dumpvars(0, RTL_tb);
end
endmodule

HM3/RTL.vcd
$date
      Sat Apr 23 15:17:33 2022

$end
$version
      Veriwell 2.8.7
$end
$timescale
      1s
$end


$scope module RTL_tb $end
$var reg       4 !    I [3:0] $end
$var wire      3 "    O [2:0] $end

$scope module RTL_tb $end
$var wire      4 #    I [3:0] $end
$var reg       3 $    O [3:1] $end
$upscope $end

$upscope $end

$enddefinitions      $end
#0
$dumpvars
b100 $
b0 #
b100 "
b0 !
$end
#1
b1 !
b1 #
#2
b10 !
b10 #
#3
b11 !
b11 #
b10 $
b10 "
#4
b100 !
b100 #
b100 $
b100 "
#5
b101 !
b101 #
b10 $
b10 "
#6
b110 !
b110 #
#7
b111 !
b111 #
b1 $
b1 "
#8
b1000 !
b1000 #
b100 $
b100 "
#9
b1001 !
b1001 #
b10 $
b10 "
#10
b1010 !
b1010 #
#11
b1011 !
b1011 #
b1 $
b1 "
#12
b1100 !
b1100 #
b10 $
b10 "
#13
b1101 !
b1101 #
b1 $
b1 "
#14
b1110 !
b1110 #
#15
b1111 !
b1111 #
