HW5/design.sv
module PRPG(clock, clr, a_out);
input clr;
input clock;

output [3:1] a_out;
reg [3:1] sreg;
initial sreg = 3'b1;
always@ (posedge clock)
    begin
        if (clr)
            sreg<=1;
        else
            sreg<={sreg[3:1],sreg[3]^sreg[1]};
    end
    
assign  a_out = sreg;
endmodule

HW5/testbench.sv
module PRPG_tb;
reg clock,clr;    //輸入
wire [3:1] a_out;   //輸出

initial begin
    #0;
    forever
    begin
        clock = 1'b0;
        #5 clock = 1'b1;
        #5;
    end
end

initial begin
    #0 clr=1'b1;  
    #10 clr=1'b0;
    #190 $finish;
end

PRPG PRPG_tb(.clock(clock), .clr(clr), .a_out(a_out));
initial begin
    $dumpfile("PRPG.vcd");
    $dumpvars(0, PRPG_tb);
end
endmodule

HW5/PRPG.vcd
$date
	Fri May 13 09:12:22 2022
$end
$version
	Icarus Verilog
$end
$timescale
	1s
$end
$scope module PRPG_tb $end
$scope module PRPG_tb $end
$var wire 3 ! a_out [3:1] $end
$var wire 1 " clock $end
$var wire 1 # clr $end
$var reg 3 $ sreg [3:1] $end
$upscope $end
$upscope $end
$enddefinitions $end
#0
$dumpvars
b1 $
1#
0"
b1 !
$end
#5
1"
#10
0"
0#
#15
b11 !
b11 $
1"
#20
0"
#25
b111 !
b111 $
1"
#30
0"
#35
b110 !
b110 $
1"
#40
0"
#45
b101 !
b101 $
1"
#50
0"
#55
b10 !
b10 $
1"
#60
0"
#65
b100 !
b100 $
1"
#70
0"
#75
b1 !
b1 $
1"
#80
0"
#85
b11 !
b11 $
1"
#90
0"
#95
b111 !
b111 $
1"
#100
0"
#105
b110 !
b110 $
1"
#110
0"
#115
b101 !
b101 $
1"
#120
0"
#125
b10 !
b10 $
1"
#130
0"
#135
b100 !
b100 $
1"
#140
0"
#145
b1 !
b1 $
1"
#150
0"
#155
b11 !
b11 $
1"
#160
0"
#165
b111 !
b111 $
1"
#170
0"
#175
b110 !
b110 $
1"
#180
0"
#185
b101 !
b101 $
1"
#190
0"
#195
b10 !
b10 $
1"
